nonebot_plugin_quickreply/__init__.py
nonebot_plugin_quickreply/config.py
nonebot_plugin_quickreply/datasource.py
nonebot_plugin_quickreply/migrations/6799b8f51dbc_first_revision.py
nonebot_plugin_quickreply/utils.py
nonebot_plugin_quickreply-0.1.16.dist-info/WHEEL
nonebot_plugin_quickreply-0.1.16.dist-info/METADATA
nonebot_plugin_quickreply-0.1.16.dist-info/RECORD
