Metadata-Version: 2.3
Name: nonebot-plugin-quickreply
Version: 0.1.16
Summary: nonebot-plugin-quickreply
Author: FlanChanXwO
Author-email: FlanChanXwO <badapple495@outlook.com>
Requires-Dist: httpx>=0.27.0,<1.0.0
Requires-Dist: nonebot-adapter-onebot>=2.4.6
Requires-Dist: nonebot2>=2.4.4
Requires-Dist: nonebot-plugin-orm>=0.8.2
Requires-Python: >=3.10
Project-URL: Homepage, https://github.com/FlanChanXwO/nonebot-plugin-quickreply
Project-URL: Issues, https://github.com/FlanChanXwO/nonebot-plugin-quickreply/issues
Project-URL: Repository, https://github.com/FlanChanXwO/nonebot-plugin-quickreply.git
